LICENSE.txt
MANIFEST.in
README.md
local-requirements.txt
pyproject.toml
setup.cfg
setup.py
setup_build.py
tox.ini
versioneer.py
src/scikits_odes_sundials/__init__.py
src/scikits_odes_sundials/_version.py
src/scikits_odes_sundials/c_cvode.pxd
src/scikits_odes_sundials/c_cvodes.pxd
src/scikits_odes_sundials/c_ida.pxd
src/scikits_odes_sundials/c_idas.pxd
src/scikits_odes_sundials/c_nvector_serial.pxd
src/scikits_odes_sundials/c_sundials.pxd
src/scikits_odes_sundials/c_sunlinsol.pxd
src/scikits_odes_sundials/c_sunmatrix.pxd
src/scikits_odes_sundials/c_sunnonlinsol.pxd
src/scikits_odes_sundials/common_defs.pxd
src/scikits_odes_sundials/common_defs.pyx
src/scikits_odes_sundials/cvode.pxd
src/scikits_odes_sundials/cvode.pyx
src/scikits_odes_sundials/cvodes.pxd
src/scikits_odes_sundials/cvodes.pyx
src/scikits_odes_sundials/ida.pxd
src/scikits_odes_sundials/ida.pyx
src/scikits_odes_sundials/idas.pxd
src/scikits_odes_sundials/idas.pyx
src/scikits_odes_sundials.egg-info/PKG-INFO
src/scikits_odes_sundials.egg-info/SOURCES.txt
src/scikits_odes_sundials.egg-info/dependency_links.txt
src/scikits_odes_sundials.egg-info/requires.txt
src/scikits_odes_sundials.egg-info/top_level.txt
src/scikits_odes_sundials/tests/__init__.py
src/scikits_odes_sundials/tests/test_helpers.py